{
  "family": "webapp-task",
  "executionRoleArn": "arn:aws:iam::216728320756:role/ecs_execution_role",
  "networkMode": "awsvpc",
  "containerDefinitions": [
    {
      "name": "webapp-container",
      "image": "216728320756.dkr.ecr.eu-central-1.amazonaws.com/aws-drf-boilerplate:latest",
      "cpu": 0,
      "portMappings": [
        {
          "containerPort": 8000,
          "hostPort": 8000,
          "protocol": "tcp"
        }
      ],
      "essential": true,
      "environment": [],
      "mountPoints": [],
      "volumesFrom": [],
      "systemControls": []
    }
  ],
  "volumes": [],
  "requiresCompatibilities": ["FARGATE"],
  "cpu": "256",
  "memory": "512"
}
